<?xml version="1.0"?>
<!DOCTYPE hibernate-mapping PUBLIC "-//Hibernate/Hibernate Mapping DTD 3.0//EN"
"http://www.hibernate.org/dtd/hibernate-mapping-3.0.dtd">
<!-- Generated Jul 5, 2015 7:44:37 AM by Hibernate Tools 4.3.1 -->
<hibernate-mapping>
    <class name="Pojo.FacturaConsulta" table="FacturaConsulta" catalog="SistemaHospital" optimistic-lock="version">
        <id name="idFactura" type="java.lang.Integer">
            <column name="id_factura" />
            <generator class="identity" />
        </id>
        <many-to-one name="cajero" class="Pojo.Cajero" fetch="select">
            <column name="id_cajero" not-null="true" />
        </many-to-one>
        <property name="horas" type="time">
            <column name="horas" length="8" not-null="true" />
        </property>
        <property name="precio" type="float">
            <column name="precio" precision="12" scale="0" not-null="true" />
        </property>
        <set name="procedimientosEspecialeses" table="ProcedimientosEspeciales" inverse="true" lazy="true" fetch="select">
            <key>
                <column name="id_factura" not-null="true" />
            </key>
            <one-to-many class="Pojo.ProcedimientosEspeciales" />
        </set>
    </class>
</hibernate-mapping>
